dash_escher/DashEscher.py
dash_escher/__init__.py
dash_escher/_imports_.py
dash_escher/dash_escher.min.js
dash_escher/dash_escher.min.js.map
dash_escher/metadata.json
dash_escher/package-info.json
dash_escher-0.0.4.dist-info/LICENSE.md
dash_escher-0.0.4.dist-info/METADATA
dash_escher-0.0.4.dist-info/WHEEL
dash_escher-0.0.4.dist-info/top_level.txt
dash_escher-0.0.4.dist-info/RECORD
